{
  "id": "task-a327e3ed",
  "epicId": "epic-daemon",
  "title": "Add moe.delete_epic MCP tool",
  "description": "Add MCP tool for epic deletion.\n\n**Implementation:**\n- Add deleteEpic.ts tool\n- Add StateManager.deleteEpic() method\n- Handle cascading: delete or orphan tasks in epic?\n- Document in MCP_SERVER.md",
  "definitionOfDone": [
    "moe.delete_epic tool implemented",
    "Handles tasks in epic appropriately",
    "Documented in MCP_SERVER.md",
    "Test added"
  ],
  "taskRails": [
    "Require confirmation or flag for epics with tasks"
  ],
  "implementationPlan": [],
  "status": "BACKLOG",
  "assignedWorkerId": null,
  "branch": null,
  "prLink": null,
  "reopenCount": 0,
  "reopenReason": null,
  "createdBy": "HUMAN",
  "parentTaskId": null,
  "order": 5,
  "createdAt": "2026-02-04T14:21:02.876Z",
  "updatedAt": "2026-02-04T14:21:02.876Z"
}