{
  "id": "task-bug-med-12",
  "epicId": "epic-bugs",
  "title": "[MEDIUM] Status bar widget initialization timing",
  "description": "File: moe-jetbrains/.../statusbar/MoeStatusBarWidget.kt\n\nIssue: Widget may display before connection established.\n\nFix: Delay initial display until state known.",
  "status": "ARCHIVED",
  "order": 33,
  "implementationPlan": [
    {
      "stepId": "step-1",
      "description": "Show 'Connecting...' status initially in widget",
      "status": "COMPLETED",
      "affectedFiles": [
        "moe-jetbrains/src/main/kotlin/com/moe/statusbar/MoeStatusBarWidget.kt"
      ],
      "startedAt": "2026-02-05T14:25:22.033Z",
      "completedAt": "2026-02-05T14:25:57.255Z"
    },
    {
      "stepId": "step-2",
      "description": "Update to actual status only after connection state is known",
      "status": "COMPLETED",
      "affectedFiles": [
        "moe-jetbrains/src/main/kotlin/com/moe/statusbar/MoeStatusBarWidget.kt"
      ],
      "startedAt": "2026-02-05T14:26:03.226Z",
      "completedAt": "2026-02-05T14:26:03.389Z"
    }
  ],
  "createdAt": "2026-02-05T15:40:00.000Z",
  "updatedAt": "2026-02-08T23:39:36.738Z",
  "assignedWorkerId": null,
  "priority": "MEDIUM",
  "comments": []
}